[{"__type__":"cc.SceneAsset","_name":"eval","scene":{"__id__":1},"asyncLoadAssets":null},{"__type__":"cc.Scene","_name":"New Node","_children":[{"__id__":2}],"_anchorPoint":{"__type__":"cc.Vec2"},"_trs":{"__type__":"TypedArray","ctor":"Float64Array","array":[0,0,0,0,0,0,1,1,1,1]},"autoReleaseAssets":false},{"__type__":"cc.Node","_name":"Canvas","_parent":{"__id__":1},"_children":[{"__id__":3},{"__id__":4}],"_components":[{"__type__":"cc.Canvas","node":{"__id__":2},"_designResolution":{"__type__":"cc.Size","width":640,"height":960},"_fitWidth":true,"_fitHeight":false},{"__type__":"cc.Widget","node":{"__id__":2},"_alignFlags":45}],"_contentSize":{"__type__":"cc.Size","width":640,"height":960},"_trs":{"__type__":"TypedArray","ctor":"Float64Array","array":[320,480,0,0,0,0,1,1,1,1]},"_id":"a5esZu+45LA5mBpvttspPD"},{"__type__":"cc.Node","_name":"Main Camera","_parent":{"__id__":2},"_components":[{"__type__":"cc.Camera","node":{"__id__":3},"_clearFlags":7,"_depth":-1}],"_contentSize":{"__type__":"cc.Size","width":960,"height":640},"_trs":{"__type__":"TypedArray","ctor":"Float64Array","array":[0,0,252.8794179050561,0,0,0,1,1,1,1]}},{"__type__":"cc.Node","_name":"eval","_parent":{"__id__":2},"_children":[{"__id__":5},{"__id__":6},{"__id__":7}],"_components":[{"__type__":"6d966F+0EdIRbcLsg1pMdtK","node":{"__id__":4},"para1":{"__id__":5},"para2":{"__id__":6},"para3":{"__id__":7}},{"__type__":"8441f8VAv9DJ5ViTs3frk2Q","node":{"__id__":4}},{"__type__":"cc.Widget","node":{"__id__":4},"alignMode":2,"_target":{"__id__":2},"_alignFlags":45,"_originalWidth":640,"_originalHeight":960}],"_contentSize":{"__type__":"cc.Size","width":640,"height":960},"_trs":{"__type__":"TypedArray","ctor":"Float64Array","array":[0,0,0,0,0,0,1,1,1,1]}},{"__type__":"cc.Node","_name":"line-1","_parent":{"__id__":4},"_components":[{"__type__":"cc.Label","node":{"__id__":5},"_materials":[{"__uuid__":"ecpdLyjvZBwrvm+cedCcQy"}],"_useOriginalSize":false,"_string":"サル以下の貴様を","_N$string":"サル以下の貴様を","_N$verticalAlign":1,"_N$overflow":2},{"__type__":"cc.Widget","node":{"__id__":5},"_target":{"__id__":4},"_alignFlags":8,"_right":320,"_originalWidth":320}],"_contentSize":{"__type__":"cc.Size","width":320,"height":50.4},"_anchorPoint":{"__type__":"cc.Vec2","y":0.5},"_trs":{"__type__":"TypedArray","ctor":"Float64Array","array":[-320,209.143,0,0,0,0,1,1,1,1]}},{"__type__":"cc.Node","_name":"line-2","_parent":{"__id__":4},"_components":[{"__type__":"cc.Label","node":{"__id__":6},"_materials":[{"__uuid__":"ecpdLyjvZBwrvm+cedCcQy"}],"_useOriginalSize":false,"_string":"便所掃除","_N$string":"便所掃除","_fontSize":80,"_lineHeight":80,"_N$horizontalAlign":1,"_N$verticalAlign":1,"_N$overflow":2},{"__type__":"cc.Widget","node":{"__id__":6},"_target":{"__id__":4},"_alignFlags":16}],"_contentSize":{"__type__":"cc.Size","width":640,"height":126},"_trs":{"__type__":"TypedArray","ctor":"Float64Array","array":[0,7.285,0,0,0,0,1,1,1,1]}},{"__type__":"cc.Node","_name":"line-3","_parent":{"__id__":4},"_components":[{"__type__":"cc.Label","node":{"__id__":7},"_materials":[{"__uuid__":"ecpdLyjvZBwrvm+cedCcQy"}],"_useOriginalSize":false,"_string":"任命する。活躍を期待する","_N$string":"任命する。活躍を期待する","_N$horizontalAlign":2,"_N$verticalAlign":1,"_N$overflow":2},{"__type__":"cc.Widget","node":{"__id__":7},"_target":{"__id__":4},"_alignFlags":32}],"_contentSize":{"__type__":"cc.Size","width":480,"height":50.4},"_anchorPoint":{"__type__":"cc.Vec2","x":1,"y":0.5},"_trs":{"__type__":"TypedArray","ctor":"Float64Array","array":[320,-183.238,0,0,0,0,1,1,1,1]}}]